autotex/__init__.py
autotex/__main__.py
autotex-0.1.dist-info/zip-safe
autotex-0.1.dist-info/entry_points.txt
autotex-0.1.dist-info/top_level.txt
autotex-0.1.dist-info/METADATA
autotex-0.1.dist-info/DESCRIPTION.rst
autotex-0.1.dist-info/metadata.json
autotex-0.1.dist-info/WHEEL
autotex-0.1.dist-info/RECORD
