Metadata-Version: 2.0
Name: autotex
Version: 0.1
Summary: UNKNOWN
Home-page: https://github.com/crepererum/hyperion
Author: Marco Neumann
Author-email: marco@crepererum.net
License: LPPL
Keywords: LaTeX
Platform: linux
Requires-Dist: msgpack-python (>=0.4.2)
Requires-Dist: pyinotify (>=0.9.4)
Requires-Dist: PyYAML (>=3.11)
Provides-Extra: dev
Requires-Dist: flake8 (>=2.2.3); extra == 'dev'
Requires-Dist: pylint (>=1.3.1); extra == 'dev'
